pytempbox/__init__.py
pytempbox/client.py
pytempbox/exceptions.py
pytempbox/utils.py
pytempbox-0.1.3.dist-info/licenses/LICENSE
pytempbox-0.1.3.dist-info/METADATA
pytempbox-0.1.3.dist-info/WHEEL
pytempbox-0.1.3.dist-info/top_level.txt
pytempbox-0.1.3.dist-info/RECORD
