Metadata-Version: 2.4
Name: pytempbox
Version: 0.1.3
Summary: Python library for temporary email addresses
Home-page: https://github.com/RozhakXD/PyTempBox
Author: Rozhak
Author-email: rozhak9@proton.me
Project-URL: Bug Reports, https://github.com/RozhakXD/PyTempBox/issues
Project-URL: Source, https://github.com/RozhakXD/PyTempBox
Keywords: temporary email,disposable email,testing,privacy
Classifier: Programming Language :: Python :: 3
Classifier: License :: OSI Approved :: MIT License
Classifier: Operating System :: OS Independent
Requires-Python: >=3.9
License-File: LICENSE
Requires-Dist: requests>=2.25.0
Dynamic: author
Dynamic: author-email
Dynamic: classifier
Dynamic: description
Dynamic: description-content-type
Dynamic: home-page
Dynamic: keywords
Dynamic: license-file
Dynamic: project-url
Dynamic: requires-dist
Dynamic: requires-python
Dynamic: summary
